apb/apb.v
module apb_slave ( 

                clk,
                preset,
                psel0,
                penable,
                pwrite,
                pwdata,
                paddr, 
                pready,
                pslverr,
                prdata
);

input clk,preset;
input  psel0,penable,pwrite;
input [7:0]  pwdata;
input [7:0] paddr;
output reg pready,pslverr;
output reg [7:0] prdata;

reg [1:0] state, next_state;
reg [7:0]mem[255:0];

parameter   IDLE = 2'b00;
parameter  SETUP = 2'b01;
parameter  ACCESS = 2'b10;

always @ (*)  begin
    if (state==ACCESS) begin
          pready<=0;
            if ( pwrite )begin
              mem [paddr] <= pwdata; 
              prdata <= 8'bx;
            end
            else prdata <= mem [paddr];  
        end
end

always @(posedge clk) begin
  if (preset) begin
     state <= IDLE ;
     pready <=1;
     pslverr <=0;
     prdata <= 8'bx;
  end
  else state <= next_state ;
end

always @(negedge clk)
     case (state)
       IDLE : begin
         next_state= psel0 ?  SETUP : IDLE ;
         pready<=1;
       end 
       SETUP : begin if (psel0 & penable) next_state = ACCESS;
               pready<=1;
               end
       ACCESS : begin
              if (!psel0) next_state = IDLE;                               
              else next_state =  penable ? ACCESS : SETUP ;
            end
    endcase
endmodule

apb/apb_tb.v
`include "apb.v"
module test ();

reg clk,preset;
reg  psel0,penable,pwrite;
reg [7:0]  pwdata;
reg [7:0] paddr;
wire pready,pslverr;
wire [7:0] prdata;

apb_slave dut (
                clk,
                preset,
                psel0,
                penable,
                pwrite,
                pwdata,
                paddr, 
                pready,
                pslverr,
                prdata );

always #2 clk=~clk;

initial begin
    reset;
    write1;
    write2;
    read1;
    read2;  
    $finish;
end

initial begin
    $dumpfile("apb.vcd");
    $dumpvars(0);
end

 task reset;
begin
    clk=0;
    preset =0;
    psel0=0;
    penable=0;
    pwrite=0;
    pwdata=0;
    paddr=0;
    #1;
    preset=1;
    #2;
    preset=0;
    #1;
end
endtask

//wrute to 25 addres
  task write2 ; 
  begin 
    paddr=25;
    pwrite=1;
    psel0=1;
    #2;
    penable=1;
    pwdata=78;
    #17;
    psel0=0;
    #6;
  end
  endtask

//read from 25 addres
task read2 ;
begin
    paddr=25;
    pwrite=0;
    psel0=1;
    #2;
    penable=1;
    pwdata=8'bx;
    #17;
    psel0=0;
    #6;
end
endtask
//write from 35 addres
task write1 ;
begin
    paddr=35;
    pwrite=1;
    psel0=1;
    #2;
    penable=1;
    pwdata=56;
    #17;
    psel0=0;
    #6;
end
endtask

//read from 35 addres
task read1;
begin
    paddr=35;
    pwrite=0;
    psel0=1;
    #2;
    penable=1;
    pwdata=8'bx;
    #17;
    psel0=0;
    #6;
end
endtask   
endmodule

apb/apb.vcd
$date
	Fri May 28 12:12:14 2021
$end
$version
	Icarus Verilog
$end
$timescale
	1s
$end
$scope module test $end
$var wire 1 ! pslverr $end
$var wire 1 " pready $end
$var wire 8 # prdata [7:0] $end
$var reg 1 $ clk $end
$var reg 8 % paddr [7:0] $end
$var reg 1 & penable $end
$var reg 1 ' preset $end
$var reg 1 ( psel0 $end
$var reg 8 ) pwdata [7:0] $end
$var reg 1 * pwrite $end
$scope module dut $end
$var wire 1 $ clk $end
$var wire 8 + paddr [7:0] $end
$var wire 1 & penable $end
$var wire 1 ' preset $end
$var wire 1 ( psel0 $end
$var wire 8 , pwdata [7:0] $end
$var wire 1 * pwrite $end
$var reg 2 - next_state [1:0] $end
$var reg 8 . prdata [7:0] $end
$var reg 1 " pready $end
$var reg 1 ! pslverr $end
$var reg 2 / state [1:0] $end
$upscope $end
$scope task read1 $end
$upscope $end
$scope task read2 $end
$upscope $end
$scope task reset $end
$upscope $end
$scope task write1 $end
$upscope $end
$scope task write2 $end
$upscope $end
$upscope $end
$enddefinitions $end
#0
$dumpvars
bx /
bx .
bx -
b0 ,
b0 +
0*
b0 )
0(
0'
0&
b0 %
0$
bx #
x"
x!
$end
#1
1'
#2
0!
1"
b0 /
1$
#3
0'
#4
b1 -
1(
1*
b100011 %
b100011 +
0$
#6
b1 /
b111000 )
b111000 ,
1&
1$
#8
b10 -
0$
#10
0"
b10 /
1$
#12
0$
#14
1$
#16
0$
#18
1$
#20
0$
#22
1$
#23
0(
#24
b0 -
0$
#26
b0 /
1$
#28
1"
0$
#29
1(
b11001 %
b11001 +
#30
1$
#31
b1001110 )
b1001110 ,
#32
b1 -
0$
#34
b1 /
1$
#36
b10 -
0$
#38
0"
b10 /
1$
#40
0$
#42
1$
#44
0$
#46
1$
#48
b0 -
0$
0(
#50
b0 /
1$
#52
1"
0$
#54
1$
1(
0*
b100011 %
b100011 +
#56
b1 -
0$
bx )
bx ,
#58
b1 /
1$
#60
b10 -
0$
#62
b111000 #
b111000 .
0"
b10 /
1$
#64
0$
#66
1$
#68
0$
#70
1$
#72
0$
#73
0(
#74
1$
#76
b0 -
0$
#78
b0 /
1$
#79
1(
b11001 %
b11001 +
#80
1"
b1 -
0$
#82
b1 /
1$
#84
b10 -
0$
#86
b1001110 #
b1001110 .
0"
b10 /
1$
#88
0$
#90
1$
#92
0$
#94
1$
#96
0$
#98
1$
0(
#100
b0 -
0$
#102
b0 /
1$
#104
1"
0$
