Traffic light controller/traffic.v
  
module traffic(x,clk,rst,Highway,Country,state);
  input x,clk,rst;
  output [1:0] Highway,Country;
  output reg [1:0] state;
  
  parameter S0=2'b00, S1=2'b01, S2=2'b10, S3=2'b11;
  parameter green=2'b00, red=2'b01, yellow=2'b10;
  reg [1:0] initial_state;
  reg [1:0] highway,country;
  parameter delay1=2;
  parameter delay2=3;
  
  	 assign Country=country;
     assign Highway=highway;
 

  
  always @ (posedge clk, rst)
    begin
      if (rst==0) begin
        initial_state<=S0;
        highway<=green;
        country<=red; end 
      else   state <= initial_state;
    end
  
  always @ (posedge clk,x,state)
    begin
      case(state)							           // HIGHwy  Country 
        S0:initial_state= x ? S1:S0; 			 //	g	     r
        S1: begin 
          repeat(delay1)@ (posedge clk);
          initial_state= S2;
    	    end							                  // 	y		 y
        S2:initial_state= x ? S2:S3;   		  //    r		 g
        S3:begin 
          repeat(delay2)@ (posedge clk);
          initial_state=S0;
        	end		                    	        //	y		y
      endcase
    end
        
  always @(state,posedge clk)
          begin
            case(state)
              S0: begin highway=green;country=red; end
              S1: begin highway=yellow;country=yellow; end
              S2: begin highway=red;country=green; end
              S3: begin highway=yellow;country=yellow; end	
            endcase
          end  
endmodule

Traffic light controller/test.v
`include "traffic.v"
module test();
  reg  x,clk,rst;
  wire [1:0] Highway,Country,state;
  
  traffic dut(x,clk,rst,Highway,Country,state);
  
  always begin #5 clk=~clk ; end
  
  initial
    begin
      x=0;
    clk=0;
    rst=1;
    #15;
     repeat(5) begin 
       #2 rst=0;
        #2 rst=1;
     end
    
    x=0;
    rst=0;
    #1;
      x=0;
    rst=1;
    #10;
      x=1;
    rst=1;
    #100;
      x=0;
    rst=1;
    #100;
     x=0;
    rst=1;
    #100;
        x=0;
    rst=0;
    #1;
      x=0;
    rst=1;
    #10;
      x=1;
    rst=1;
    #100;
      x=0;
    rst=1;
    #100;
     x=0;
    rst=1;
    #100;
    $finish;
  end
  
  initial begin
     $dumpfile("file.vcd");
    $dumpvars(1);
  end
endmodule

Traffic light controller/file.vcd
$date
	Fri May 28 12:58:16 2021
$end
$version
	Icarus Verilog
$end
$timescale
	1s
$end
$scope module test $end
$var wire 2 ! state [1:0] $end
$var wire 2 " Highway [1:0] $end
$var wire 2 # Country [1:0] $end
$var reg 1 $ clk $end
$var reg 1 % rst $end
$var reg 1 & x $end
$upscope $end
$enddefinitions $end
#0
$dumpvars
0&
1%
0$
bx #
bx "
bx !
$end
#5
1$
#10
0$
#15
1$
#17
b1 #
b0 "
0%
#19
b0 !
1%
#20
0$
#21
0%
#23
1%
#25
0%
1$
#27
1%
#29
0%
#30
0$
#31
1%
#33
0%
#35
0%
1$
#36
1%
#40
0$
#45
1$
#46
1&
#50
0$
#55
b10 #
b10 "
b1 !
1$
#60
0$
#65
1$
#70
0$
#75
1$
#80
0$
#85
b0 #
b1 "
b10 !
1$
#90
0$
#95
1$
#100
0$
#105
1$
#110
0$
#115
1$
#120
0$
#125
1$
#130
0$
#135
1$
#140
0$
#145
1$
#146
0&
#150
0$
#155
b10 #
b10 "
b11 !
1$
#160
0$
#165
1$
#170
0$
#175
1$
#180
0$
#185
1$
#190
0$
#195
b1 #
b0 "
b0 !
1$
#200
0$
#205
1$
#210
0$
#215
1$
#220
0$
#225
1$
#230
0$
#235
1$
#240
0$
#245
1$
#250
0$
#255
1$
#260
0$
#265
1$
#270
0$
#275
1$
#280
0$
#285
1$
#290
0$
#295
1$
#300
0$
#305
1$
#310
0$
#315
1$
#320
0$
#325
1$
#330
0$
#335
1$
#340
0$
#345
1$
#346
0%
#347
1%
#350
0$
#355
1$
#357
1&
#360
0$
#365
b10 #
b10 "
b1 !
1$
#370
0$
#375
1$
#380
0$
#385
1$
#390
0$
#395
b0 #
b1 "
b10 !
1$
#400
0$
#405
1$
#410
0$
#415
1$
#420
0$
#425
1$
#430
0$
#435
1$
#440
0$
#445
1$
#450
0$
#455
1$
#457
0&
#460
0$
#465
b10 #
b10 "
b11 !
1$
#470
0$
#475
1$
#480
0$
#485
1$
#490
0$
#495
1$
#500
0$
#505
b1 #
b0 "
b0 !
1$
