2 stage pipelined_adder/adder_16bit_piplined.v
module adder_16 (clk,A,B,SUM,Cout);
    input clk;
    input [7:0] A,B;
    output [7:0] SUM;
    output Cout;
    
    reg  CARRYi;
    wire  CARRYo;

assign {CARRYo,SUM[3:0]}= A[3:0] + B[3:0];
assign {Cout,SUM[7:4]}= A[7:4] + B[7:4]+ CARRYi;

always @(posedge clk) begin
    CARRYi<=CARRYo;
end
endmodule

2 stage pipelined_adder/adder_tb.v
`include "adder_16bit_piplined.v"
module adder_tb ();

    reg clk;
    reg [7:0] A,B;
    wire  [7:0] SUM;
    wire Cout;
    integer i,j=0;
    reg  CARRYi;
    wire  CARRYo;

    adder_16 dut (clk,A,B,SUM,Cout);

    always  #5 clk=~clk;

    initial begin
        clk=0;
        $dumpfile("adder.vcd");
        $dumpvars(0);

        for(i=0;i<=15;i=i+1) begin
            for(j=0;j<=15;j=j+1) begin
            A<=i;
            B<=j;
            #30;
            end
        end
        B=255;
        A=255;
        #40;
        $finish;
    end   
endmodule

2 stage pipelined_adder/adder.vcd
$date
	Fri May 14 13:57:39 2021
$end
$version
	Icarus Verilog
$end
$timescale
	1s
$end
$scope module adder_tb $end
$var wire 8 ! SUM [7:0] $end
$var wire 1 " Cout $end
$var reg 8 # A [7:0] $end
$var reg 8 $ B [7:0] $end
$var reg 1 % clk $end
$var integer 32 & i [31:0] $end
$var integer 32 ' j [31:0] $end
$scope module dut $end
$var wire 8 ( A [7:0] $end
$var wire 8 ) B [7:0] $end
$var wire 1 % clk $end
$var wire 8 * SUM [7:0] $end
$var wire 1 " Cout $end
$var wire 1 + CARRYo $end
$var reg 1 , CARRYi $end
$upscope $end
$upscope $end
$enddefinitions $end
#0
$dumpvars
x,
0+
bx0000 *
b0 )
b0 (
b0 '
b0 &
0%
b0 $
b0 #
x"
bx0000 !
$end
#5
b0 !
b0 *
0"
0,
1%
#10
0%
#15
1%
#20
0%
#25
1%
#30
b1 !
b1 *
b1 $
b1 )
0%
b1 '
#35
1%
#40
0%
#45
1%
#50
0%
#55
1%
#60
b10 !
b10 *
b10 $
b10 )
0%
b10 '
#65
1%
#70
0%
#75
1%
#80
0%
#85
1%
#90
b11 !
b11 *
b11 $
b11 )
0%
b11 '
#95
1%
#100
0%
#105
1%
#110
0%
#115
1%
#120
b100 !
b100 *
b100 $
b100 )
0%
b100 '
#125
1%
#130
0%
#135
1%
#140
0%
#145
1%
#150
b101 !
b101 *
b101 $
b101 )
0%
b101 '
#155
1%
#160
0%
#165
1%
#170
0%
#175
1%
#180
b110 !
b110 *
b110 $
b110 )
0%
b110 '
#185
1%
#190
0%
#195
1%
#200
0%
#205
1%
#210
b111 !
b111 *
b111 $
b111 )
0%
b111 '
#215
1%
#220
0%
#225
1%
#230
0%
#235
1%
#240
b1000 !
b1000 *
b1000 $
b1000 )
0%
b1000 '
#245
1%
#250
0%
#255
1%
#260
0%
#265
1%
#270
b1001 !
b1001 *
b1001 $
b1001 )
0%
b1001 '
#275
1%
#280
0%
#285
1%
#290
0%
#295
1%
#300
b1010 !
b1010 *
b1010 $
b1010 )
0%
b1010 '
#305
1%
#310
0%
#315
1%
#320
0%
#325
1%
#330
b1011 !
b1011 *
b1011 $
b1011 )
0%
b1011 '
#335
1%
#340
0%
#345
1%
#350
0%
#355
1%
#360
b1100 !
b1100 *
b1100 $
b1100 )
0%
b1100 '
#365
1%
#370
0%
#375
1%
#380
0%
#385
1%
#390
b1101 !
b1101 *
b1101 $
b1101 )
0%
b1101 '
#395
1%
#400
0%
#405
1%
#410
0%
#415
1%
#420
b1110 !
b1110 *
b1110 $
b1110 )
0%
b1110 '
#425
1%
#430
0%
#435
1%
#440
0%
#445
1%
#450
b1111 !
b1111 *
b1111 $
b1111 )
0%
b1111 '
#455
1%
#460
0%
#465
1%
#470
0%
#475
1%
#480
b1 !
b1 *
b0 $
b0 )
b1 #
b1 (
0%
b1 &
b0 '
#485
1%
#490
0%
#495
1%
#500
0%
#505
1%
#510
b10 !
b10 *
b1 $
b1 )
0%
b1 '
#515
1%
#520
0%
#525
1%
#530
0%
#535
1%
#540
b11 !
b11 *
b10 $
b10 )
0%
b10 '
#545
1%
#550
0%
#555
1%
#560
0%
#565
1%
#570
b100 !
b100 *
b11 $
b11 )
0%
b11 '
#575
1%
#580
0%
#585
1%
#590
0%
#595
1%
#600
b101 !
b101 *
b100 $
b100 )
0%
b100 '
#605
1%
#610
0%
#615
1%
#620
0%
#625
1%
#630
b110 !
b110 *
b101 $
b101 )
0%
b101 '
#635
1%
#640
0%
#645
1%
#650
0%
#655
1%
#660
b111 !
b111 *
b110 $
b110 )
0%
b110 '
#665
1%
#670
0%
#675
1%
#680
0%
#685
1%
#690
b1000 !
b1000 *
b111 $
b111 )
0%
b111 '
#695
1%
#700
0%
#705
1%
#710
0%
#715
1%
#720
b1001 !
b1001 *
b1000 $
b1000 )
0%
b1000 '
#725
1%
#730
0%
#735
1%
#740
0%
#745
1%
#750
b1010 !
b1010 *
b1001 $
b1001 )
0%
b1001 '
#755
1%
#760
0%
#765
1%
#770
0%
#775
1%
#780
b1011 !
b1011 *
b1010 $
b1010 )
0%
b1010 '
#785
1%
#790
0%
#795
1%
#800
0%
#805
1%
#810
b1100 !
b1100 *
b1011 $
b1011 )
0%
b1011 '
#815
1%
#820
0%
#825
1%
#830
0%
#835
1%
#840
b1101 !
b1101 *
b1100 $
b1100 )
0%
b1100 '
#845
1%
#850
0%
#855
1%
#860
0%
#865
1%
#870
b1110 !
b1110 *
b1101 $
b1101 )
0%
b1101 '
#875
1%
#880
0%
#885
1%
#890
0%
#895
1%
#900
b1111 !
b1111 *
b1110 $
b1110 )
0%
b1110 '
#905
1%
#910
0%
#915
1%
#920
0%
#925
1%
#930
b0 !
b0 *
1+
b1111 $
b1111 )
0%
b1111 '
#935
b10000 !
b10000 *
1,
1%
#940
0%
#945
1%
#950
0%
#955
1%
#960
0+
b10010 !
b10010 *
b0 $
b0 )
b10 #
b10 (
0%
b10 &
b0 '
#965
b10 !
b10 *
0,
1%
#970
0%
#975
1%
#980
0%
#985
1%
#990
b11 !
b11 *
b1 $
b1 )
0%
b1 '
#995
1%
#1000
0%
#1005
1%
#1010
0%
#1015
1%
#1020
b100 !
b100 *
b10 $
b10 )
0%
b10 '
#1025
1%
#1030
0%
#1035
1%
#1040
0%
#1045
1%
#1050
b101 !
b101 *
b11 $
b11 )
0%
b11 '
#1055
1%
#1060
0%
#1065
1%
#1070
0%
#1075
1%
#1080
b110 !
b110 *
b100 $
b100 )
0%
b100 '
#1085
1%
#1090
0%
#1095
1%
#1100
0%
#1105
1%
#1110
b111 !
b111 *
b101 $
b101 )
0%
b101 '
#1115
1%
#1120
0%
#1125
1%
#1130
0%
#1135
1%
#1140
b1000 !
b1000 *
b110 $
b110 )
0%
b110 '
#1145
1%
#1150
0%
#1155
1%
#1160
0%
#1165
1%
#1170
b1001 !
b1001 *
b111 $
b111 )
0%
b111 '
#1175
1%
#1180
0%
#1185
1%
#1190
0%
#1195
1%
#1200
b1010 !
b1010 *
b1000 $
b1000 )
0%
b1000 '
#1205
1%
#1210
0%
#1215
1%
#1220
0%
#1225
1%
#1230
b1011 !
b1011 *
b1001 $
b1001 )
0%
b1001 '
#1235
1%
#1240
0%
#1245
1%
#1250
0%
#1255
1%
#1260
b1100 !
b1100 *
b1010 $
b1010 )
0%
b1010 '
#1265
1%
#1270
0%
#1275
1%
#1280
0%
#1285
1%
#1290
b1101 !
b1101 *
b1011 $
b1011 )
0%
b1011 '
#1295
1%
#1300
0%
#1305
1%
#1310
0%
#1315
1%
#1320
b1110 !
b1110 *
b1100 $
b1100 )
0%
b1100 '
#1325
1%
#1330
0%
#1335
1%
#1340
0%
#1345
1%
#1350
b1111 !
b1111 *
b1101 $
b1101 )
0%
b1101 '
#1355
1%
#1360
0%
#1365
1%
#1370
0%
#1375
1%
#1380
b0 !
b0 *
1+
b1110 $
b1110 )
0%
b1110 '
#1385
b10000 !
b10000 *
1,
1%
#1390
0%
#1395
1%
#1400
0%
#1405
1%
#1410
b10001 !
b10001 *
b1111 $
b1111 )
0%
b1111 '
#1415
1%
#1420
0%
#1425
1%
#1430
0%
#1435
1%
#1440
0+
b10011 !
b10011 *
b0 $
b0 )
b11 #
b11 (
0%
b11 &
b0 '
#1445
b11 !
b11 *
0,
1%
#1450
0%
#1455
1%
#1460
0%
#1465
1%
#1470
b100 !
b100 *
b1 $
b1 )
0%
b1 '
#1475
1%
#1480
0%
#1485
1%
#1490
0%
#1495
1%
#1500
b101 !
b101 *
b10 $
b10 )
0%
b10 '
#1505
1%
#1510
0%
#1515
1%
#1520
0%
#1525
1%
#1530
b110 !
b110 *
b11 $
b11 )
0%
b11 '
#1535
1%
#1540
0%
#1545
1%
#1550
0%
#1555
1%
#1560
b111 !
b111 *
b100 $
b100 )
0%
b100 '
#1565
1%
#1570
0%
#1575
1%
#1580
0%
#1585
1%
#1590
b1000 !
b1000 *
b101 $
b101 )
0%
b101 '
#1595
1%
#1600
0%
#1605
1%
#1610
0%
#1615
1%
#1620
b1001 !
b1001 *
b110 $
b110 )
0%
b110 '
#1625
1%
#1630
0%
#1635
1%
#1640
0%
#1645
1%
#1650
b1010 !
b1010 *
b111 $
b111 )
0%
b111 '
#1655
1%
#1660
0%
#1665
1%
#1670
0%
#1675
1%
#1680
b1011 !
b1011 *
b1000 $
b1000 )
0%
b1000 '
#1685
1%
#1690
0%
#1695
1%
#1700
0%
#1705
1%
#1710
b1100 !
b1100 *
b1001 $
b1001 )
0%
b1001 '
#1715
1%
#1720
0%
#1725
1%
#1730
0%
#1735
1%
#1740
b1101 !
b1101 *
b1010 $
b1010 )
0%
b1010 '
#1745
1%
#1750
0%
#1755
1%
#1760
0%
#1765
1%
#1770
b1110 !
b1110 *
b1011 $
b1011 )
0%
b1011 '
#1775
1%
#1780
0%
#1785
1%
#1790
0%
#1795
1%
#1800
b1111 !
b1111 *
b1100 $
b1100 )
0%
b1100 '
#1805
1%
#1810
0%
#1815
1%
#1820
0%
#1825
1%
#1830
b0 !
b0 *
1+
b1101 $
b1101 )
0%
b1101 '
#1835
b10000 !
b10000 *
1,
1%
#1840
0%
#1845
1%
#1850
0%
#1855
1%
#1860
b10001 !
b10001 *
b1110 $
b1110 )
0%
b1110 '
#1865
1%
#1870
0%
#1875
1%
#1880
0%
#1885
1%
#1890
b10010 !
b10010 *
b1111 $
b1111 )
0%
b1111 '
#1895
1%
#1900
0%
#1905
1%
#1910
0%
#1915
1%
#1920
0+
b10100 !
b10100 *
b0 $
b0 )
b100 #
b100 (
0%
b100 &
b0 '
#1925
b100 !
b100 *
0,
1%
#1930
0%
#1935
1%
#1940
0%
#1945
1%
#1950
b101 !
b101 *
b1 $
b1 )
0%
b1 '
#1955
1%
#1960
0%
#1965
1%
#1970
0%
#1975
1%
#1980
b110 !
b110 *
b10 $
b10 )
0%
b10 '
#1985
1%
#1990
0%
#1995
1%
#2000
0%
#2005
1%
#2010
b111 !
b111 *
b11 $
b11 )
0%
b11 '
#2015
1%
#2020
0%
#2025
1%
#2030
0%
#2035
1%
#2040
b1000 !
b1000 *
b100 $
b100 )
0%
b100 '
#2045
1%
#2050
0%
#2055
1%
#2060
0%
#2065
1%
#2070
b1001 !
b1001 *
b101 $
b101 )
0%
b101 '
#2075
1%
#2080
0%
#2085
1%
#2090
0%
#2095
1%
#2100
b1010 !
b1010 *
b110 $
b110 )
0%
b110 '
#2105
1%
#2110
0%
#2115
1%
#2120
0%
#2125
1%
#2130
b1011 !
b1011 *
b111 $
b111 )
0%
b111 '
#2135
1%
#2140
0%
#2145
1%
#2150
0%
#2155
1%
#2160
b1100 !
b1100 *
b1000 $
b1000 )
0%
b1000 '
#2165
1%
#2170
0%
#2175
1%
#2180
0%
#2185
1%
#2190
b1101 !
b1101 *
b1001 $
b1001 )
0%
b1001 '
#2195
1%
#2200
0%
#2205
1%
#2210
0%
#2215
1%
#2220
b1110 !
b1110 *
b1010 $
b1010 )
0%
b1010 '
#2225
1%
#2230
0%
#2235
1%
#2240
0%
#2245
1%
#2250
b1111 !
b1111 *
b1011 $
b1011 )
0%
b1011 '
#2255
1%
#2260
0%
#2265
1%
#2270
0%
#2275
1%
#2280
b0 !
b0 *
1+
b1100 $
b1100 )
0%
b1100 '
#2285
b10000 !
b10000 *
1,
1%
#2290
0%
#2295
1%
#2300
0%
#2305
1%
#2310
b10001 !
b10001 *
b1101 $
b1101 )
0%
b1101 '
#2315
1%
#2320
0%
#2325
1%
#2330
0%
#2335
1%
#2340
b10010 !
b10010 *
b1110 $
b1110 )
0%
b1110 '
#2345
1%
#2350
0%
#2355
1%
#2360
0%
#2365
1%
#2370
b10011 !
b10011 *
b1111 $
b1111 )
0%
b1111 '
#2375
1%
#2380
0%
#2385
1%
#2390
0%
#2395
1%
#2400
0+
b10101 !
b10101 *
b0 $
b0 )
b101 #
b101 (
0%
b101 &
b0 '
#2405
b101 !
b101 *
0,
1%
#2410
0%
#2415
1%
#2420
0%
#2425
1%
#2430
b110 !
b110 *
b1 $
b1 )
0%
b1 '
#2435
1%
#2440
0%
#2445
1%
#2450
0%
#2455
1%
#2460
b111 !
b111 *
b10 $
b10 )
0%
b10 '
#2465
1%
#2470
0%
#2475
1%
#2480
0%
#2485
1%
#2490
b1000 !
b1000 *
b11 $
b11 )
0%
b11 '
#2495
1%
#2500
0%
#2505
1%
#2510
0%
#2515
1%
#2520
b1001 !
b1001 *
b100 $
b100 )
0%
b100 '
#2525
1%
#2530
0%
#2535
1%
#2540
0%
#2545
1%
#2550
b1010 !
b1010 *
b101 $
b101 )
0%
b101 '
#2555
1%
#2560
0%
#2565
1%
#2570
0%
#2575
1%
#2580
b1011 !
b1011 *
b110 $
b110 )
0%
b110 '
#2585
1%
#2590
0%
#2595
1%
#2600
0%
#2605
1%
#2610
b1100 !
b1100 *
b111 $
b111 )
0%
b111 '
#2615
1%
#2620
0%
#2625
1%
#2630
0%
#2635
1%
#2640
b1101 !
b1101 *
b1000 $
b1000 )
0%
b1000 '
#2645
1%
#2650
0%
#2655
1%
#2660
0%
#2665
1%
#2670
b1110 !
b1110 *
b1001 $
b1001 )
0%
b1001 '
#2675
1%
#2680
0%
#2685
1%
#2690
0%
#2695
1%
#2700
b1111 !
b1111 *
b1010 $
b1010 )
0%
b1010 '
#2705
1%
#2710
0%
#2715
1%
#2720
0%
#2725
1%
#2730
b0 !
b0 *
1+
b1011 $
b1011 )
0%
b1011 '
#2735
b10000 !
b10000 *
1,
1%
#2740
0%
#2745
1%
#2750
0%
#2755
1%
#2760
b10001 !
b10001 *
b1100 $
b1100 )
0%
b1100 '
#2765
1%
#2770
0%
#2775
1%
#2780
0%
#2785
1%
#2790
b10010 !
b10010 *
b1101 $
b1101 )
0%
b1101 '
#2795
1%
#2800
0%
#2805
1%
#2810
0%
#2815
1%
#2820
b10011 !
b10011 *
b1110 $
b1110 )
0%
b1110 '
#2825
1%
#2830
0%
#2835
1%
#2840
0%
#2845
1%
#2850
b10100 !
b10100 *
b1111 $
b1111 )
0%
b1111 '
#2855
1%
#2860
0%
#2865
1%
#2870
0%
#2875
1%
#2880
0+
b10110 !
b10110 *
b0 $
b0 )
b110 #
b110 (
0%
b110 &
b0 '
#2885
b110 !
b110 *
0,
1%
#2890
0%
#2895
1%
#2900
0%
#2905
1%
#2910
b111 !
b111 *
b1 $
b1 )
0%
b1 '
#2915
1%
#2920
0%
#2925
1%
#2930
0%
#2935
1%
#2940
b1000 !
b1000 *
b10 $
b10 )
0%
b10 '
#2945
1%
#2950
0%
#2955
1%
#2960
0%
#2965
1%
#2970
b1001 !
b1001 *
b11 $
b11 )
0%
b11 '
#2975
1%
#2980
0%
#2985
1%
#2990
0%
#2995
1%
#3000
b1010 !
b1010 *
b100 $
b100 )
0%
b100 '
#3005
1%
#3010
0%
#3015
1%
#3020
0%
#3025
1%
#3030
b1011 !
b1011 *
b101 $
b101 )
0%
b101 '
#3035
1%
#3040
0%
#3045
1%
#3050
0%
#3055
1%
#3060
b1100 !
b1100 *
b110 $
b110 )
0%
b110 '
#3065
1%
#3070
0%
#3075
1%
#3080
0%
#3085
1%
#3090
b1101 !
b1101 *
b111 $
b111 )
0%
b111 '
#3095
1%
#3100
0%
#3105
1%
#3110
0%
#3115
1%
#3120
b1110 !
b1110 *
b1000 $
b1000 )
0%
b1000 '
#3125
1%
#3130
0%
#3135
1%
#3140
0%
#3145
1%
#3150
b1111 !
b1111 *
b1001 $
b1001 )
0%
b1001 '
#3155
1%
#3160
0%
#3165
1%
#3170
0%
#3175
1%
#3180
b0 !
b0 *
1+
b1010 $
b1010 )
0%
b1010 '
#3185
b10000 !
b10000 *
1,
1%
#3190
0%
#3195
1%
#3200
0%
#3205
1%
#3210
b10001 !
b10001 *
b1011 $
b1011 )
0%
b1011 '
#3215
1%
#3220
0%
#3225
1%
#3230
0%
#3235
1%
#3240
b10010 !
b10010 *
b1100 $
b1100 )
0%
b1100 '
#3245
1%
#3250
0%
#3255
1%
#3260
0%
#3265
1%
#3270
b10011 !
b10011 *
b1101 $
b1101 )
0%
b1101 '
#3275
1%
#3280
0%
#3285
1%
#3290
0%
#3295
1%
#3300
b10100 !
b10100 *
b1110 $
b1110 )
0%
b1110 '
#3305
1%
#3310
0%
#3315
1%
#3320
0%
#3325
1%
#3330
b10101 !
b10101 *
b1111 $
b1111 )
0%
b1111 '
#3335
1%
#3340
0%
#3345
1%
#3350
0%
#3355
1%
#3360
0+
b10111 !
b10111 *
b0 $
b0 )
b111 #
b111 (
0%
b111 &
b0 '
#3365
b111 !
b111 *
0,
1%
#3370
0%
#3375
1%
#3380
0%
#3385
1%
#3390
b1000 !
b1000 *
b1 $
b1 )
0%
b1 '
#3395
1%
#3400
0%
#3405
1%
#3410
0%
#3415
1%
#3420
b1001 !
b1001 *
b10 $
b10 )
0%
b10 '
#3425
1%
#3430
0%
#3435
1%
#3440
0%
#3445
1%
#3450
b1010 !
b1010 *
b11 $
b11 )
0%
b11 '
#3455
1%
#3460
0%
#3465
1%
#3470
0%
#3475
1%
#3480
b1011 !
b1011 *
b100 $
b100 )
0%
b100 '
#3485
1%
#3490
0%
#3495
1%
#3500
0%
#3505
1%
#3510
b1100 !
b1100 *
b101 $
b101 )
0%
b101 '
#3515
1%
#3520
0%
#3525
1%
#3530
0%
#3535
1%
#3540
b1101 !
b1101 *
b110 $
b110 )
0%
b110 '
#3545
1%
#3550
0%
#3555
1%
#3560
0%
#3565
1%
#3570
b1110 !
b1110 *
b111 $
b111 )
0%
b111 '
#3575
1%
#3580
0%
#3585
1%
#3590
0%
#3595
1%
#3600
b1111 !
b1111 *
b1000 $
b1000 )
0%
b1000 '
#3605
1%
#3610
0%
#3615
1%
#3620
0%
#3625
1%
#3630
b0 !
b0 *
1+
b1001 $
b1001 )
0%
b1001 '
#3635
b10000 !
b10000 *
1,
1%
#3640
0%
#3645
1%
#3650
0%
#3655
1%
#3660
b10001 !
b10001 *
b1010 $
b1010 )
0%
b1010 '
#3665
1%
#3670
0%
#3675
1%
#3680
0%
#3685
1%
#3690
b10010 !
b10010 *
b1011 $
b1011 )
0%
b1011 '
#3695
1%
#3700
0%
#3705
1%
#3710
0%
#3715
1%
#3720
b10011 !
b10011 *
b1100 $
b1100 )
0%
b1100 '
#3725
1%
#3730
0%
#3735
1%
#3740
0%
#3745
1%
#3750
b10100 !
b10100 *
b1101 $
b1101 )
0%
b1101 '
#3755
1%
#3760
0%
#3765
1%
#3770
0%
#3775
1%
#3780
b10101 !
b10101 *
b1110 $
b1110 )
0%
b1110 '
#3785
1%
#3790
0%
#3795
1%
#3800
0%
#3805
1%
#3810
b10110 !
b10110 *
b1111 $
b1111 )
0%
b1111 '
#3815
1%
#3820
0%
#3825
1%
#3830
0%
#3835
1%
#3840
0+
b11000 !
b11000 *
b0 $
b0 )
b1000 #
b1000 (
0%
b1000 &
b0 '
#3845
b1000 !
b1000 *
0,
1%
#3850
0%
#3855
1%
#3860
0%
#3865
1%
#3870
b1001 !
b1001 *
b1 $
b1 )
0%
b1 '
#3875
1%
#3880
0%
#3885
1%
#3890
0%
#3895
1%
#3900
b1010 !
b1010 *
b10 $
b10 )
0%
b10 '
#3905
1%
#3910
0%
#3915
1%
#3920
0%
#3925
1%
#3930
b1011 !
b1011 *
b11 $
b11 )
0%
b11 '
#3935
1%
#3940
0%
#3945
1%
#3950
0%
#3955
1%
#3960
b1100 !
b1100 *
b100 $
b100 )
0%
b100 '
#3965
1%
#3970
0%
#3975
1%
#3980
0%
#3985
1%
#3990
b1101 !
b1101 *
b101 $
b101 )
0%
b101 '
#3995
1%
#4000
0%
#4005
1%
#4010
0%
#4015
1%
#4020
b1110 !
b1110 *
b110 $
b110 )
0%
b110 '
#4025
1%
#4030
0%
#4035
1%
#4040
0%
#4045
1%
#4050
b1111 !
b1111 *
b111 $
b111 )
0%
b111 '
#4055
1%
#4060
0%
#4065
1%
#4070
0%
#4075
1%
#4080
b0 !
b0 *
1+
b1000 $
b1000 )
0%
b1000 '
#4085
b10000 !
b10000 *
1,
1%
#4090
0%
#4095
1%
#4100
0%
#4105
1%
#4110
b10001 !
b10001 *
b1001 $
b1001 )
0%
b1001 '
#4115
1%
#4120
0%
#4125
1%
#4130
0%
#4135
1%
#4140
b10010 !
b10010 *
b1010 $
b1010 )
0%
b1010 '
#4145
1%
#4150
0%
#4155
1%
#4160
0%
#4165
1%
#4170
b10011 !
b10011 *
b1011 $
b1011 )
0%
b1011 '
#4175
1%
#4180
0%
#4185
1%
#4190
0%
#4195
1%
#4200
b10100 !
b10100 *
b1100 $
b1100 )
0%
b1100 '
#4205
1%
#4210
0%
#4215
1%
#4220
0%
#4225
1%
#4230
b10101 !
b10101 *
b1101 $
b1101 )
0%
b1101 '
#4235
1%
#4240
0%
#4245
1%
#4250
0%
#4255
1%
#4260
b10110 !
b10110 *
b1110 $
b1110 )
0%
b1110 '
#4265
1%
#4270
0%
#4275
1%
#4280
0%
#4285
1%
#4290
b10111 !
b10111 *
b1111 $
b1111 )
0%
b1111 '
#4295
1%
#4300
0%
#4305
1%
#4310
0%
#4315
1%
#4320
0+
b11001 !
b11001 *
b0 $
b0 )
b1001 #
b1001 (
0%
b1001 &
b0 '
#4325
b1001 !
b1001 *
0,
1%
#4330
0%
#4335
1%
#4340
0%
#4345
1%
#4350
b1010 !
b1010 *
b1 $
b1 )
0%
b1 '
#4355
1%
#4360
0%
#4365
1%
#4370
0%
#4375
1%
#4380
b1011 !
b1011 *
b10 $
b10 )
0%
b10 '
#4385
1%
#4390
0%
#4395
1%
#4400
0%
#4405
1%
#4410
b1100 !
b1100 *
b11 $
b11 )
0%
b11 '
#4415
1%
#4420
0%
#4425
1%
#4430
0%
#4435
1%
#4440
b1101 !
b1101 *
b100 $
b100 )
0%
b100 '
#4445
1%
#4450
0%
#4455
1%
#4460
0%
#4465
1%
#4470
b1110 !
b1110 *
b101 $
b101 )
0%
b101 '
#4475
1%
#4480
0%
#4485
1%
#4490
0%
#4495
1%
#4500
b1111 !
b1111 *
b110 $
b110 )
0%
b110 '
#4505
1%
#4510
0%
#4515
1%
#4520
0%
#4525
1%
#4530
b0 !
b0 *
1+
b111 $
b111 )
0%
b111 '
#4535
b10000 !
b10000 *
1,
1%
#4540
0%
#4545
1%
#4550
0%
#4555
1%
#4560
b10001 !
b10001 *
b1000 $
b1000 )
0%
b1000 '
#4565
1%
#4570
0%
#4575
1%
#4580
0%
#4585
1%
#4590
b10010 !
b10010 *
b1001 $
b1001 )
0%
b1001 '
#4595
1%
#4600
0%
#4605
1%
#4610
0%
#4615
1%
#4620
b10011 !
b10011 *
b1010 $
b1010 )
0%
b1010 '
#4625
1%
#4630
0%
#4635
1%
#4640
0%
#4645
1%
#4650
b10100 !
b10100 *
b1011 $
b1011 )
0%
b1011 '
#4655
1%
#4660
0%
#4665
1%
#4670
0%
#4675
1%
#4680
b10101 !
b10101 *
b1100 $
b1100 )
0%
b1100 '
#4685
1%
#4690
0%
#4695
1%
#4700
0%
#4705
1%
#4710
b10110 !
b10110 *
b1101 $
b1101 )
0%
b1101 '
#4715
1%
#4720
0%
#4725
1%
#4730
0%
#4735
1%
#4740
b10111 !
b10111 *
b1110 $
b1110 )
0%
b1110 '
#4745
1%
#4750
0%
#4755
1%
#4760
0%
#4765
1%
#4770
b11000 !
b11000 *
b1111 $
b1111 )
0%
b1111 '
#4775
1%
#4780
0%
#4785
1%
#4790
0%
#4795
1%
#4800
0+
b11010 !
b11010 *
b0 $
b0 )
b1010 #
b1010 (
0%
b1010 &
b0 '
#4805
b1010 !
b1010 *
0,
1%
#4810
0%
#4815
1%
#4820
0%
#4825
1%
#4830
b1011 !
b1011 *
b1 $
b1 )
0%
b1 '
#4835
1%
#4840
0%
#4845
1%
#4850
0%
#4855
1%
#4860
b1100 !
b1100 *
b10 $
b10 )
0%
b10 '
#4865
1%
#4870
0%
#4875
1%
#4880
0%
#4885
1%
#4890
b1101 !
b1101 *
b11 $
b11 )
0%
b11 '
#4895
1%
#4900
0%
#4905
1%
#4910
0%
#4915
1%
#4920
b1110 !
b1110 *
b100 $
b100 )
0%
b100 '
#4925
1%
#4930
0%
#4935
1%
#4940
0%
#4945
1%
#4950
b1111 !
b1111 *
b101 $
b101 )
0%
b101 '
#4955
1%
#4960
0%
#4965
1%
#4970
0%
#4975
1%
#4980
b0 !
b0 *
1+
b110 $
b110 )
0%
b110 '
#4985
b10000 !
b10000 *
1,
1%
#4990
0%
#4995
1%
#5000
0%
#5005
1%
#5010
b10001 !
b10001 *
b111 $
b111 )
0%
b111 '
#5015
1%
#5020
0%
#5025
1%
#5030
0%
#5035
1%
#5040
b10010 !
b10010 *
b1000 $
b1000 )
0%
b1000 '
#5045
1%
#5050
0%
#5055
1%
#5060
0%
#5065
1%
#5070
b10011 !
b10011 *
b1001 $
b1001 )
0%
b1001 '
#5075
1%
#5080
0%
#5085
1%
#5090
0%
#5095
1%
#5100
b10100 !
b10100 *
b1010 $
b1010 )
0%
b1010 '
#5105
1%
#5110
0%
#5115
1%
#5120
0%
#5125
1%
#5130
b10101 !
b10101 *
b1011 $
b1011 )
0%
b1011 '
#5135
1%
#5140
0%
#5145
1%
#5150
0%
#5155
1%
#5160
b10110 !
b10110 *
b1100 $
b1100 )
0%
b1100 '
#5165
1%
#5170
0%
#5175
1%
#5180
0%
#5185
1%
#5190
b10111 !
b10111 *
b1101 $
b1101 )
0%
b1101 '
#5195
1%
#5200
0%
#5205
1%
#5210
0%
#5215
1%
#5220
b11000 !
b11000 *
b1110 $
b1110 )
0%
b1110 '
#5225
1%
#5230
0%
#5235
1%
#5240
0%
#5245
1%
#5250
b11001 !
b11001 *
b1111 $
b1111 )
0%
b1111 '
#5255
1%
#5260
0%
#5265
1%
#5270
0%
#5275
1%
#5280
0+
b11011 !
b11011 *
b0 $
b0 )
b1011 #
b1011 (
0%
b1011 &
b0 '
#5285
b1011 !
b1011 *
0,
1%
#5290
0%
#5295
1%
#5300
0%
#5305
1%
#5310
b1100 !
b1100 *
b1 $
b1 )
0%
b1 '
#5315
1%
#5320
0%
#5325
1%
#5330
0%
#5335
1%
#5340
b1101 !
b1101 *
b10 $
b10 )
0%
b10 '
#5345
1%
#5350
0%
#5355
1%
#5360
0%
#5365
1%
#5370
b1110 !
b1110 *
b11 $
b11 )
0%
b11 '
#5375
1%
#5380
0%
#5385
1%
#5390
0%
#5395
1%
#5400
b1111 !
b1111 *
b100 $
b100 )
0%
b100 '
#5405
1%
#5410
0%
#5415
1%
#5420
0%
#5425
1%
#5430
b0 !
b0 *
1+
b101 $
b101 )
0%
b101 '
#5435
b10000 !
b10000 *
1,
1%
#5440
0%
#5445
1%
#5450
0%
#5455
1%
#5460
b10001 !
b10001 *
b110 $
b110 )
0%
b110 '
#5465
1%
#5470
0%
#5475
1%
#5480
0%
#5485
1%
#5490
b10010 !
b10010 *
b111 $
b111 )
0%
b111 '
#5495
1%
#5500
0%
#5505
1%
#5510
0%
#5515
1%
#5520
b10011 !
b10011 *
b1000 $
b1000 )
0%
b1000 '
#5525
1%
#5530
0%
#5535
1%
#5540
0%
#5545
1%
#5550
b10100 !
b10100 *
b1001 $
b1001 )
0%
b1001 '
#5555
1%
#5560
0%
#5565
1%
#5570
0%
#5575
1%
#5580
b10101 !
b10101 *
b1010 $
b1010 )
0%
b1010 '
#5585
1%
#5590
0%
#5595
1%
#5600
0%
#5605
1%
#5610
b10110 !
b10110 *
b1011 $
b1011 )
0%
b1011 '
#5615
1%
#5620
0%
#5625
1%
#5630
0%
#5635
1%
#5640
b10111 !
b10111 *
b1100 $
b1100 )
0%
b1100 '
#5645
1%
#5650
0%
#5655
1%
#5660
0%
#5665
1%
#5670
b11000 !
b11000 *
b1101 $
b1101 )
0%
b1101 '
#5675
1%
#5680
0%
#5685
1%
#5690
0%
#5695
1%
#5700
b11001 !
b11001 *
b1110 $
b1110 )
0%
b1110 '
#5705
1%
#5710
0%
#5715
1%
#5720
0%
#5725
1%
#5730
b11010 !
b11010 *
b1111 $
b1111 )
0%
b1111 '
#5735
1%
#5740
0%
#5745
1%
#5750
0%
#5755
1%
#5760
0+
b11100 !
b11100 *
b0 $
b0 )
b1100 #
b1100 (
0%
b1100 &
b0 '
#5765
b1100 !
b1100 *
0,
1%
#5770
0%
#5775
1%
#5780
0%
#5785
1%
#5790
b1101 !
b1101 *
b1 $
b1 )
0%
b1 '
#5795
1%
#5800
0%
#5805
1%
#5810
0%
#5815
1%
#5820
b1110 !
b1110 *
b10 $
b10 )
0%
b10 '
#5825
1%
#5830
0%
#5835
1%
#5840
0%
#5845
1%
#5850
b1111 !
b1111 *
b11 $
b11 )
0%
b11 '
#5855
1%
