bidirectional_port/bothside.v
module bothside (
 in ,out,control);
    inout in;
    inout out;
    input control;

    
bufif1 b1 (out,in,control);
bufif0 b2  (in,out,control);

endmodule

bidirectional_port/bothside_tb.v
`include "bothside.v"

module bothside_tb_in ();
wire in;
wire out;
reg control;
reg a,b;
integer i=0;
bothside dut (in,out,control);

assign in = control ? a:1'bz;
assign out = control ?1'bz :b;

initial begin
    $dumpfile("file.vcd");
    $dumpvars(0);
    #10;

    while (i<8) begin
        {control,a,b}=i;
        #5;
        i=i+1;
        $display("For control %b , in= %b   ,out= %b",control,in,out);
        if (i==7)$finish;
    end
end
endmodule

bidirectional_port/file.vcd
$date
	Sat May 15 12:00:54 2021
$end
$version
	Icarus Verilog
$end
$timescale
	1s
$end
$scope module bothside_tb_in $end
$var wire 1 ! in $end
$var wire 1 " out $end
$var reg 1 # a $end
$var reg 1 $ b $end
$var reg 1 % control $end
$var integer 32 & i [31:0] $end
$scope module dut $end
$var wire 1 % control $end
$var wire 1 ! in $end
$var wire 1 " out $end
$upscope $end
$upscope $end
$enddefinitions $end
#0
$dumpvars
b0 &
x%
x$
x#
x"
x!
$end
#10
0!
0"
0%
0#
0$
#15
1!
1"
1$
b1 &
#20
0!
0"
1#
0$
b10 &
#25
1!
1"
1$
b11 &
#30
0"
0!
1%
0#
0$
b100 &
#35
1$
b101 &
#40
1"
1!
1#
0$
b110 &
#45
b111 &
