half_adder/half_adder.v
module half_adder(input A,B, output S,C);

assign S= A^B;
assign C= A&B;

endmodule

full_adder/full_adder.v
module full_adder (
    input A,B,Cin,output S,Cout
);
    
    wire w1,w2,w3;
    half_adder dut1 (A,B,w1,w2);
    half_adder dut2 (w1,Cin,S,w3);
    or or1 (Cout,w2,w3);
    

endmodule

full_adder/full_adder_tb.v
module full_adder_tb (
    a,b,c,sum,carry);


output reg a,b,c;
input sum,carry;


full_adder  tb_instance (
                    .A(a),
                    .B(b),
                    .Cin(c),
                    .S(sum),
                    .Cout(carry)
                    );


integer  i;

    initial begin
        $dumpfile("full_adder.vcd");
        $dumpvars(1);


        for (i=0;i<8;i=i+1) begin
            {a,b,c}=i;
            #10;
        end
        end

    
endmodule

full_adder/full_adder.vcd
$date
	Mon May 10 19:45:51 2021
$end
$version
	Icarus Verilog
$end
$timescale
	1s
$end
$scope module full_adder_tb $end
$var wire 1 ! sum $end
$var wire 1 " carry $end
$var reg 1 # a $end
$var reg 1 $ b $end
$var reg 1 % c $end
$var integer 32 & i [31:0] $end
$upscope $end
$enddefinitions $end
#0
$dumpvars
b0 &
0%
0$
0#
0"
0!
$end
#10
1!
1%
b1 &
#20
1!
1$
0%
b10 &
#30
1"
0!
1%
b11 &
#40
0"
1!
1#
0$
0%
b100 &
#50
1"
0!
1%
b101 &
#60
0!
1$
0%
b110 &
#70
1!
1%
b111 &
#80
b1000 &
